mlca/__init__.py
mlca/_version.py
mlca/main.py
mlca/mlc_analyzer.py
mlca/options.py
mlca/utilities.py
tests/__init__.py
tests/test_mlc_analyzer.py
tests/test_utilities.py
dvha_mlca-0.2.3.post1.dist-info/LICENSE
dvha_mlca-0.2.3.post1.dist-info/METADATA
dvha_mlca-0.2.3.post1.dist-info/WHEEL
dvha_mlca-0.2.3.post1.dist-info/entry_points.txt
dvha_mlca-0.2.3.post1.dist-info/top_level.txt
dvha_mlca-0.2.3.post1.dist-info/RECORD
