Metadata-Version: 2.1
Name: dvha-mlca
Version: 0.2.3.post1
Summary: Batch analyze DICOM-RT Plan files to calculate Complexity Scores
Home-page: https://github.com/cutright/DVHA-MLCA
Author: Dan Cutright
Author-email: dan.cutright@gmail.com
License: MIT License
Download-URL: https://github.com/cutright/DVHA-MLCA/archive/master.zip
Keywords: radiation therapy,research,dicom,dicom-rt,analytics
Platform: UNKNOWN
Classifier: License :: OSI Approved :: MIT License
Classifier: Intended Audience :: End Users/Desktop
Classifier: Intended Audience :: Healthcare Industry
Classifier: Intended Audience :: Science/Research
Classifier: Natural Language :: English
Classifier: Development Status :: 4 - Beta
Classifier: Programming Language :: Python
Classifier: Programming Language :: Python :: 3.6
Classifier: Programming Language :: Python :: 3.7
Classifier: Programming Language :: Python :: 3.8
Classifier: Programming Language :: Python :: 3.9
Classifier: Operating System :: OS Independent
Classifier: Topic :: Scientific/Engineering :: Medical Science Apps.
Classifier: Topic :: Scientific/Engineering :: Physics
Requires-Python: >3.5
Requires-Dist: numpy
Requires-Dist: pydicom
Requires-Dist: shapely[vectorized]
Requires-Dist: tqdm
